rtctools_channel_flow/__init__.py
rtctools_channel_flow/_version.py
rtctools_channel_flow/modelica/Deltares/Constants.mo
rtctools_channel_flow/modelica/Deltares/package.mo
rtctools_channel_flow/modelica/Deltares/ChannelFlow/package.mo
rtctools_channel_flow/modelica/Deltares/ChannelFlow/package.order
rtctools_channel_flow/modelica/Deltares/ChannelFlow/Hydraulic/package.mo
rtctools_channel_flow/modelica/Deltares/ChannelFlow/Hydraulic/package.order
rtctools_channel_flow/modelica/Deltares/ChannelFlow/Hydraulic/BoundaryConditions/Discharge.mo
rtctools_channel_flow/modelica/Deltares/ChannelFlow/Hydraulic/BoundaryConditions/Level.mo
rtctools_channel_flow/modelica/Deltares/ChannelFlow/Hydraulic/BoundaryConditions/package.mo
rtctools_channel_flow/modelica/Deltares/ChannelFlow/Hydraulic/BoundaryConditions/package.order
rtctools_channel_flow/modelica/Deltares/ChannelFlow/Hydraulic/Branches/HomotopicLinear.mo
rtctools_channel_flow/modelica/Deltares/ChannelFlow/Hydraulic/Branches/HomotopicTrapezoidal.mo
rtctools_channel_flow/modelica/Deltares/ChannelFlow/Hydraulic/Branches/Linear.mo
rtctools_channel_flow/modelica/Deltares/ChannelFlow/Hydraulic/Branches/package.mo
rtctools_channel_flow/modelica/Deltares/ChannelFlow/Hydraulic/Branches/package.order
rtctools_channel_flow/modelica/Deltares/ChannelFlow/Hydraulic/Branches/Internal/BottomFrictionCoefficient.mo
rtctools_channel_flow/modelica/Deltares/ChannelFlow/Hydraulic/Branches/Internal/PartialHomotopic.mo
rtctools_channel_flow/modelica/Deltares/ChannelFlow/Hydraulic/Branches/Internal/package.mo
rtctools_channel_flow/modelica/Deltares/ChannelFlow/Hydraulic/Branches/Internal/package.order
rtctools_channel_flow/modelica/Deltares/ChannelFlow/Hydraulic/Reservoir/HomotopicPower.mo
rtctools_channel_flow/modelica/Deltares/ChannelFlow/Hydraulic/Reservoir/HomotopicVolume.mo
rtctools_channel_flow/modelica/Deltares/ChannelFlow/Hydraulic/Reservoir/Linear.mo
rtctools_channel_flow/modelica/Deltares/ChannelFlow/Hydraulic/Reservoir/package.mo
rtc_tools_channel_flow-1.3.0.dist-info/COPYING.LESSER
rtc_tools_channel_flow-1.3.0.dist-info/METADATA
rtc_tools_channel_flow-1.3.0.dist-info/WHEEL
rtc_tools_channel_flow-1.3.0.dist-info/entry_points.txt
rtc_tools_channel_flow-1.3.0.dist-info/top_level.txt
rtc_tools_channel_flow-1.3.0.dist-info/RECORD
