Metadata-Version: 2.1
Name: rtc-tools-channel-flow
Version: 1.3.0
Summary: Simple and hydraulic Modelica routing models for RTC-Tools 2.
Home-page: http://www.deltares.nl/en/software/rtc-tools/
Author: Deltares
Maintainer: Deltares
License: LGPL
Download-URL: http://gitlab.com/deltares/rtc-tools-channel-flow/
Platform: Windows
Platform: Linux
Platform: Mac OS-X
Platform: Unix
Classifier: Intended Audience :: Science/Research
Classifier: Intended Audience :: Information Technology
Classifier: License :: OSI Approved :: GNU Lesser General Public License v3 (LGPLv3)
Classifier: Programming Language :: Other
Classifier: Topic :: Scientific/Engineering :: GIS
Classifier: Topic :: Scientific/Engineering :: Mathematics
Classifier: Topic :: Scientific/Engineering :: Physics
Classifier: Operating System :: Microsoft :: Windows
Classifier: Operating System :: POSIX
Classifier: Operating System :: Unix
Classifier: Operating System :: MacOS
License-File: COPYING.LESSER
